{
    "data": {
        "attributes": {
            "type_description": "ZIP",
            "tlsh": "T19797332EC8FD63CBDE3F253EDD149B27C2A5C29D5682B079AD448B651DC73D842BA804",
            "vhash": "f8b39694dbbf5dab21c6e69e24e00010",
            "trid": [
                {
                    "file_type": "Mozilla Archive Format (gen)",
                    "probability": 58.3
                },
                {
                    "file_type": "ZIP compressed archive",
                    "probability": 33.3
                },
                {
                    "file_type": "PrintFox/Pagefox bitmap (640x800)",
                    "probability": 8.3
                }
            ],
            "names": [
                "AetherSX2-alpha-1860-mac.zip"
            ],
            "last_modification_date": 1653097240,
            "type_tag": "zip",
            "times_submitted": 2,
            "total_votes": {
                "harmless": 0,
                "malicious": 0
            },
            "size": 42489536,
            "type_extension": "zip",
            "last_submission_date": 1653050081,
            "last_analysis_results": {
                "Bkav": {
                    "category": "undetected",
                    "engine_name": "Bkav",
                    "engine_version": "1.3.0.9899",
                    "result": null,
                    "method": "blacklist",
                    "engine_update": "20220520"
                },
                "Lionic": {
                    "category": "undetected",
                    "engine_name": "Lionic",
                    "engine_version": "7.5",
                    "result": null,
                    "method": "blacklist",
                    "engine_update": "20220520"
                },
                "Elastic": {
                    "category": "type-unsupported",
                    "engine_name": "Elastic",
                    "engine_version": "4.0.37",
                    "result": null,
                    "method": "blacklist",
                    "engine_update": "20220520"
                },
                "MicroWorld-eScan": {
                    "category": "undetected",
                    "engine_name": "MicroWorld-eScan",
                    "engine_version": "14.0.409.0",
                    "result": null,
                    "method": "blacklist",
                    "engine_update": "20220520"
                },
                "FireEye": {
                    "category": "undetected",
                    "engine_name": "FireEye",
                    "engine_version": "35.24.1.0",
                    "result": null,
                    "method": "blacklist",
                    "engine_update": "20220520"
                },
                "CAT-QuickHeal": {
                    "category": "undetected",
                    "engine_name": "CAT-QuickHeal",
                    "engine_version": "14.00",
                    "result": null,
                    "method": "blacklist",
                    "engine_update": "20220520"
                },
                "McAfee": {
                    "category": "undetected",
                    "engine_name": "McAfee",
                    "engine_version": "6.0.6.653",
                    "result": null,
                    "method": "blacklist",
                    "engine_update": "20220520"
                },
                "Cylance": {
                    "category": "type-unsupported",
                    "engine_name": "Cylance",
                    "engine_version": "2.3.1.101",
                    "result": null,
                    "method": "blacklist",
                    "engine_update": "20220520"
                },
                "Sangfor": {
                    "category": "confirmed-timeout",
                    "engine_name": "Sangfor",
                    "engine_version": "2.14.0.0",
                    "result": null,
                    "method": "blacklist",
                    "engine_update": "20220520"
                },
                "Trustlook": {
                    "category": "undetected",
                    "engine_name": "Trustlook",
                    "engine_version": "1.0",
                    "result": null,
                    "method": "blacklist",
                    "engine_update": "20220520"
                },
                "BitDefender": {
                    "category": "undetected",
                    "engine_name": "BitDefender",
                    "engine_version": "7.2",
                    "result": null,
                    "method": "blacklist",
                    "engine_update": "20220520"
                },
                "K7GW": {
                    "category": "undetected",
                    "engine_name": "K7GW",
                    "engine_version": "12.13.42421",
                    "result": null,
                    "method": "blacklist",
                    "engine_update": "20220520"
                },
                "K7AntiVirus": {
                    "category": "undetected",
                    "engine_name": "K7AntiVirus",
                    "engine_version": "12.13.42419",
                    "result": null,
                    "method": "blacklist",
                    "engine_update": "20220520"
                },
                "Baidu": {
                    "category": "undetected",
                    "engine_name": "Baidu",
                    "engine_version": "1.0.0.2",
                    "result": null,
                    "method": "blacklist",
                    "engine_update": "20190318"
                },
                "VirIT": {
                    "category": "undetected",
                    "engine_name": "VirIT",
                    "engine_version": "9.5.200",
                    "result": null,
                    "method": "blacklist",
                    "engine_update": "20220520"
                },
                "Cyren": {
                    "category": "undetected",
                    "engine_name": "Cyren",
                    "engine_version": "6.5.1.2",
                    "result": null,
                    "method": "blacklist",
                    "engine_update": "20220520"
                },
                "SymantecMobileInsight": {
                    "category": "type-unsupported",
                    "engine_name": "SymantecMobileInsight",
                    "engine_version": "2.0",
                    "result": null,
                    "method": "blacklist",
                    "engine_update": "20220208"
                },
                "Symantec": {
                    "category": "undetected",
                    "engine_name": "Symantec",
                    "engine_version": "1.17.0.0",
                    "result": null,
                    "method": "blacklist",
                    "engine_update": "20220520"
                },
                "tehtris": {
                    "category": "type-unsupported",
                    "engine_name": "tehtris",
                    "engine_version": "v0.1.2",
                    "result": null,
                    "method": "blacklist",
                    "engine_update": "20220520"
                },
                "ESET-NOD32": {
                    "category": "undetected",
                    "engine_name": "ESET-NOD32",
                    "engine_version": "25302",
                    "result": null,
                    "method": "blacklist",
                    "engine_update": "20220520"
                },
                "APEX": {
                    "category": "type-unsupported",
                    "engine_name": "APEX",
                    "engine_version": "6.293",
                    "result": null,
                    "method": "blacklist",
                    "engine_update": "20220519"
                },
                "TrendMicro-HouseCall": {
                    "category": "undetected",
                    "engine_name": "TrendMicro-HouseCall",
                    "engine_version": "10.0.0.1040",
                    "result": null,
                    "method": "blacklist",
                    "engine_update": "20220520"
                },
                "Avast": {
                    "category": "undetected",
                    "engine_name": "Avast",
                    "engine_version": "21.1.5827.0",
                    "result": null,
                    "method": "blacklist",
                    "engine_update": "20220520"
                },
                "ClamAV": {
                    "category": "undetected",
                    "engine_name": "ClamAV",
                    "engine_version": "0.105.0.0",
                    "result": null,
                    "method": "blacklist",
                    "engine_update": "20220520"
                },
                "Kaspersky": {
                    "category": "undetected",
                    "engine_name": "Kaspersky",
                    "engine_version": "21.0.1.45",
                    "result": null,
                    "method": "blacklist",
                    "engine_update": "20220520"
                },
                "Alibaba": {
                    "category": "undetected",
                    "engine_name": "Alibaba",
                    "engine_version": "0.3.0.5",
                    "result": null,
                    "method": "blacklist",
                    "engine_update": "20190527"
                },
                "NANO-Antivirus": {
                    "category": "undetected",
                    "engine_name": "NANO-Antivirus",
                    "engine_version": "1.0.146.25588",
                    "result": null,
                    "method": "blacklist",
                    "engine_update": "20220520"
                },
                "ViRobot": {
                    "category": "undetected",
                    "engine_name": "ViRobot",
                    "engine_version": "2014.3.20.0",
                    "result": null,
                    "method": "blacklist",
                    "engine_update": "20220520"
                },
                "Rising": {
                    "category": "undetected",
                    "engine_name": "Rising",
                    "engine_version": "25.0.0.27",
                    "result": null,
                    "method": "blacklist",
                    "engine_update": "20220520"
                },
                "Ad-Aware": {
                    "category": "undetected",
                    "engine_name": "Ad-Aware",
                    "engine_version": "3.0.21.193",
                    "result": null,
                    "method": "blacklist",
                    "engine_update": "20220520"
                },
                "Comodo": {
                    "category": "undetected",
                    "engine_name": "Comodo",
                    "engine_version": "34639",
                    "result": null,
                    "method": "blacklist",
                    "engine_update": "20220520"
                },
                "F-Secure": {
                    "category": "undetected",
                    "engine_name": "F-Secure",
                    "engine_version": "18.10.978.51",
                    "result": null,
                    "method": "blacklist",
                    "engine_update": "20220520"
                },
                "DrWeb": {
                    "category": "undetected",
                    "engine_name": "DrWeb",
                    "engine_version": "7.0.56.4040",
                    "result": null,
                    "method": "blacklist",
                    "engine_update": "20220520"
                },
                "Zillya": {
                    "category": "undetected",
                    "engine_name": "Zillya",
                    "engine_version": "2.0.0.4635",
                    "result": null,
                    "method": "blacklist",
                    "engine_update": "20220519"
                },
                "TrendMicro": {
                    "category": "undetected",
                    "engine_name": "TrendMicro",
                    "engine_version": "11.0.0.1006",
                    "result": null,
                    "method": "blacklist",
                    "engine_update": "20220520"
                },
                "McAfee-GW-Edition": {
                    "category": "undetected",
                    "engine_name": "McAfee-GW-Edition",
                    "engine_version": "v2019.1.2+3728",
                    "result": null,
                    "method": "blacklist",
                    "engine_update": "20220520"
                },
                "SentinelOne": {
                    "category": "type-unsupported",
                    "engine_name": "SentinelOne",
                    "engine_version": "22.2.1.2",
                    "result": null,
                    "method": "blacklist",
                    "engine_update": "20220330"
                },
                "Trapmine": {
                    "category": "type-unsupported",
                    "engine_name": "Trapmine",
                    "engine_version": "3.5.48.1",
                    "result": null,
                    "method": "blacklist",
                    "engine_update": "20220419"
                },
                "CMC": {
                    "category": "undetected",
                    "engine_name": "CMC",
                    "engine_version": "2.10.2019.1",
                    "result": null,
                    "method": "blacklist",
                    "engine_update": "20211026"
                },
                "Sophos": {
                    "category": "undetected",
                    "engine_name": "Sophos",
                    "engine_version": "1.4.1.0",
                    "result": null,
                    "method": "blacklist",
                    "engine_update": "20220520"
                },
                "Paloalto": {
                    "category": "type-unsupported",
                    "engine_name": "Paloalto",
                    "engine_version": "0.9.0.1003",
                    "result": null,
                    "method": "blacklist",
                    "engine_update": "20220520"
                },
                "GData": {
                    "category": "undetected",
                    "engine_name": "GData",
                    "engine_version": "A:25.33079B:27.27426",
                    "result": null,
                    "method": "blacklist",
                    "engine_update": "20220520"
                },
                "Jiangmin": {
                    "category": "undetected",
                    "engine_name": "Jiangmin",
                    "engine_version": "16.0.100",
                    "result": null,
                    "method": "blacklist",
                    "engine_update": "20220520"
                },
                "Webroot": {
                    "category": "type-unsupported",
                    "engine_name": "Webroot",
                    "engine_version": "1.0.0.403",
                    "result": null,
                    "method": "blacklist",
                    "engine_update": "20220520"
                },
                "Avira": {
                    "category": "undetected",
                    "engine_name": "Avira",
                    "engine_version": "8.3.3.14",
                    "result": null,
                    "method": "blacklist",
                    "engine_update": "20220520"
                },
                "Kingsoft": {
                    "category": "undetected",
                    "engine_name": "Kingsoft",
                    "engine_version": "2017.9.26.565",
                    "result": null,
                    "method": "blacklist",
                    "engine_update": "20220520"
                },
                "Microsoft": {
                    "category": "undetected",
                    "engine_name": "Microsoft",
                    "engine_version": "1.1.19200.6",
                    "result": null,
                    "method": "blacklist",
                    "engine_update": "20220520"
                },
                "Gridinsoft": {
                    "category": "undetected",
                    "engine_name": "Gridinsoft",
                    "engine_version": "1.0.78.174",
                    "result": null,
                    "method": "blacklist",
                    "engine_update": "20220520"
                },
                "Arcabit": {
                    "category": "undetected",
                    "engine_name": "Arcabit",
                    "engine_version": "1.0.0.889",
                    "result": null,
                    "method": "blacklist",
                    "engine_update": "20220520"
                },
                "SUPERAntiSpyware": {
                    "category": "undetected",
                    "engine_name": "SUPERAntiSpyware",
                    "engine_version": "5.6.0.1032",
                    "result": null,
                    "method": "blacklist",
                    "engine_update": "20220514"
                },
                "ZoneAlarm": {
                    "category": "undetected",
                    "engine_name": "ZoneAlarm",
                    "engine_version": "1.0",
                    "result": null,
                    "method": "blacklist",
                    "engine_update": "20220520"
                },
                "Avast-Mobile": {
                    "category": "undetected",
                    "engine_name": "Avast-Mobile",
                    "engine_version": "220520-00",
                    "result": null,
                    "method": "blacklist",
                    "engine_update": "20220520"
                },
                "TACHYON": {
                    "category": "undetected",
                    "engine_name": "TACHYON",
                    "engine_version": "2022-05-20.02",
                    "result": null,
                    "method": "blacklist",
                    "engine_update": "20220520"
                },
                "BitDefenderFalx": {
                    "category": "type-unsupported",
                    "engine_name": "BitDefenderFalx",
                    "engine_version": "2.0.936",
                    "result": null,
                    "method": "blacklist",
                    "engine_update": "20220103"
                },
                "AhnLab-V3": {
                    "category": "undetected",
                    "engine_name": "AhnLab-V3",
                    "engine_version": "3.21.3.10230",
                    "result": null,
                    "method": "blacklist",
                    "engine_update": "20220520"
                },
                "Acronis": {
                    "category": "undetected",
                    "engine_name": "Acronis",
                    "engine_version": "1.2.0.108",
                    "result": null,
                    "method": "blacklist",
                    "engine_update": "20220426"
                },
                "ALYac": {
                    "category": "undetected",
                    "engine_name": "ALYac",
                    "engine_version": "1.1.3.1",
                    "result": null,
                    "method": "blacklist",
                    "engine_update": "20220520"
                },
                "MAX": {
                    "category": "undetected",
                    "engine_name": "MAX",
                    "engine_version": "2019.9.16.1",
                    "result": null,
                    "method": "blacklist",
                    "engine_update": "20220520"
                },
                "VBA32": {
                    "category": "undetected",
                    "engine_name": "VBA32",
                    "engine_version": "5.0.0",
                    "result": null,
                    "method": "blacklist",
                    "engine_update": "20220520"
                },
                "Zoner": {
                    "category": "undetected",
                    "engine_name": "Zoner",
                    "engine_version": "2.2.2.0",
                    "result": null,
                    "method": "blacklist",
                    "engine_update": "20220520"
                },
                "Tencent": {
                    "category": "undetected",
                    "engine_name": "Tencent",
                    "engine_version": "1.0.0.1",
                    "result": null,
                    "method": "blacklist",
                    "engine_update": "20220520"
                },
                "Yandex": {
                    "category": "undetected",
                    "engine_name": "Yandex",
                    "engine_version": "5.5.2.24",
                    "result": null,
                    "method": "blacklist",
                    "engine_update": "20220428"
                },
                "Ikarus": {
                    "category": "undetected",
                    "engine_name": "Ikarus",
                    "engine_version": "6.0.24.0",
                    "result": null,
                    "method": "blacklist",
                    "engine_update": "20220520"
                },
                "MaxSecure": {
                    "category": "undetected",
                    "engine_name": "MaxSecure",
                    "engine_version": "1.0.0.1",
                    "result": null,
                    "method": "blacklist",
                    "engine_update": "20220520"
                },
                "Fortinet": {
                    "category": "undetected",
                    "engine_name": "Fortinet",
                    "engine_version": "6.2.142.0",
                    "result": null,
                    "method": "blacklist",
                    "engine_update": "20220520"
                },
                "BitDefenderTheta": {
                    "category": "undetected",
                    "engine_name": "BitDefenderTheta",
                    "engine_version": "7.2.37796.0",
                    "result": null,
                    "method": "blacklist",
                    "engine_update": "20220518"
                },
                "Cybereason": {
                    "category": "type-unsupported",
                    "engine_name": "Cybereason",
                    "engine_version": "1.2.449",
                    "result": null,
                    "method": "blacklist",
                    "engine_update": "20210330"
                },
                "Panda": {
                    "category": "undetected",
                    "engine_name": "Panda",
                    "engine_version": "4.6.4.2",
                    "result": null,
                    "method": "blacklist",
                    "engine_update": "20220520"
                },
                "CrowdStrike": {
                    "category": "type-unsupported",
                    "engine_name": "CrowdStrike",
                    "engine_version": "1.0",
                    "result": null,
                    "method": "blacklist",
                    "engine_update": "20220418"
                }
            },
            "crowdsourced_ids_stats": {
                "info": 1,
                "high": 0,
                "medium": 0,
                "low": 1
            },
            "sha256": "37728c0ac7b9e14722a4bdb1e2df2c54353a9f8379243faeddaacacbae29e40b",
            "tags": [
                "mac-app",
                "contains-macho",
                "zip"
            ],
            "crowdsourced_ids_results": [
                {
                    "rule_category": "unknown",
                    "alert_severity": "low",
                    "rule_msg": "(http_inspect) HTTP Content-Length message body was truncated",
                    "rule_raw": "alert ( gid:119; sid:260; rev:1; msg:\"(http_inspect) HTTP Content-Length message body was truncated\"; metadata: rule-type preproc; classtype:unknown;)",
                    "alert_context": [
                        {
                            "dest_port": 80,
                            "dest_ip": "184.28.221.115"
                        }
                    ],
                    "rule_url": "https://www.snort.org/downloads/#rule-downloads",
                    "rule_source": "Snort registered user ruleset",
                    "rule_id": "119:260"
                },
                {
                    "rule_category": "policy-violation",
                    "alert_severity": "info",
                    "rule_msg": "APP-DETECT Apple Messages push.apple.com DNS TXT request attempt",
                    "rule_raw": "alert udp $HOME_NET any -> any 53 ( msg:\"APP-DETECT Apple Messages push.apple.com DNS TXT request attempt\"; flow:to_server; byte_test:1,!&,0xF8,2; content:\"|04|push|05|apple|03|com|00 00 10 00 01|\",fast_pattern,nocase; metadata:policy max-detect-ips drop; service:dns; reference:url,www.apple.com/osx/apps/all.html#messages; classtype:policy-violation; sid:25080; rev:2; )",
                    "rule_references": [
                        "https://www.apple.com/osx/apps/all.html#messages"
                    ],
                    "rule_url": "https://www.snort.org/downloads/#rule-downloads",
                    "rule_source": "Snort registered user ruleset",
                    "rule_id": "1:25080"
                }
            ],
            "last_analysis_date": 1653089791,
            "unique_sources": 2,
            "first_submission_date": 1651752031,
            "ssdeep": "786432:tFbYwrBrZL+XqOXQcn5g4Gvg4Gig4GocR6B3u4uwuqLIH22zU5k9mop5hjDdEe:9dlyXtFyvYvBvocY1u4uwuzH22zapopf",
            "bundle_info": {
                "highest_datetime": "2022-05-04 06:15:20",
                "lowest_datetime": "2021-11-10 02:15:28",
                "num_children": 194,
                "extensions": {
                    "zip": 2,
                    "fx": 1,
                    "prl": 15,
                    "txt": 1,
                    "ttf": 3,
                    "png": 1
                },
                "file_types": {
                    "XML": 27,
                    "ZIP": 2,
                    "unknown": 39,
                    "directory": 61,
                    "Mac OS X Executable": 64,
                    "PNG": 1
                },
                "type": "ZIP",
                "uncompressed_size": 105493100
            },
            "md5": "c759923102aa1ece8e58a89c29d347f2",
            "sha1": "8ca56c9312ab32d0aff29917f3315948954503a2",
            "magic": "Zip archive data, at least v1.0 to extract",
            "last_analysis_stats": {
                "harmless": 0,
                "type-unsupported": 12,
                "suspicious": 0,
                "confirmed-timeout": 1,
                "timeout": 0,
                "failure": 0,
                "malicious": 0,
                "undetected": 56
            },
            "meaningful_name": "AetherSX2-alpha-1860-mac.zip",
            "reputation": 0
        },
        "type": "file",
        "id": "37728c0ac7b9e14722a4bdb1e2df2c54353a9f8379243faeddaacacbae29e40b",
        "links": {
            "self": "https://www.virustotal.com/api/v3/files/37728c0ac7b9e14722a4bdb1e2df2c54353a9f8379243faeddaacacbae29e40b"
        }
    }
}