{
    "data": {
        "id": "9bf23a643558a5a0b2ed1e9cd265ab7227cd31b2ae1ffb7e5c26c5806b2995ec",
        "type": "file",
        "links": {
            "self": "https://www.virustotal.com/api/v3/files/9bf23a643558a5a0b2ed1e9cd265ab7227cd31b2ae1ffb7e5c26c5806b2995ec"
        },
        "attributes": {
            "type_description": "JAR",
            "magic": "Zip archive data, at least v1.0 to extract, compression method=store",
            "last_submission_date": 1714057823,
            "reputation": 0,
            "vhash": "c388698490e381e12cc7b2511ddc73b5",
            "type_tags": [
                "compressed",
                "jar"
            ],
            "first_submission_date": 1714057823,
            "type_tag": "jar",
            "size": 128204899,
            "tlsh": "T1D458332185A95D25D70B73353250B74141C96DEB2216EC7FF78882FDAFA26E39232C8D",
            "sha256": "9bf23a643558a5a0b2ed1e9cd265ab7227cd31b2ae1ffb7e5c26c5806b2995ec",
            "sha1": "041077502dfd62fe6ebd688f4b95d137ac0da0cc",
            "names": [
                "WireframeSketcher-7.1.1-macosx.arm64.zip"
            ],
            "total_votes": {
                "harmless": 0,
                "malicious": 0
            },
            "last_analysis_results": {
                "Bkav": {
                    "method": "blacklist",
                    "engine_name": "Bkav",
                    "engine_version": "2.0.0.1",
                    "engine_update": "20240425",
                    "category": "undetected",
                    "result": null
                },
                "tehtris": {
                    "method": "blacklist",
                    "engine_name": "tehtris",
                    "engine_version": "v0.1.4",
                    "engine_update": "20240425",
                    "category": "undetected",
                    "result": null
                },
                "MicroWorld-eScan": {
                    "method": "blacklist",
                    "engine_name": "MicroWorld-eScan",
                    "engine_version": "14.0.409.0",
                    "engine_update": "20240425",
                    "category": "undetected",
                    "result": null
                },
                "ClamAV": {
                    "method": "blacklist",
                    "engine_name": "ClamAV",
                    "engine_version": "1.3.1.0",
                    "engine_update": "20240425",
                    "category": "undetected",
                    "result": null
                },
                "CMC": {
                    "method": "blacklist",
                    "engine_name": "CMC",
                    "engine_version": "2.4.2022.1",
                    "engine_update": "20240423",
                    "category": "undetected",
                    "result": null
                },
                "CAT-QuickHeal": {
                    "method": "blacklist",
                    "engine_name": "CAT-QuickHeal",
                    "engine_version": "22.00",
                    "engine_update": "20240424",
                    "category": "undetected",
                    "result": null
                },
                "Malwarebytes": {
                    "method": "blacklist",
                    "engine_name": "Malwarebytes",
                    "engine_version": "4.5.5.54",
                    "engine_update": "20240425",
                    "category": "undetected",
                    "result": null
                },
                "Sangfor": {
                    "method": "blacklist",
                    "engine_name": "Sangfor",
                    "engine_version": "2.23.0.0",
                    "engine_update": "20240423",
                    "category": "undetected",
                    "result": null
                },
                "Trustlook": {
                    "method": "blacklist",
                    "engine_name": "Trustlook",
                    "engine_version": "1.0",
                    "engine_update": "20240425",
                    "category": "undetected",
                    "result": null
                },
                "K7GW": {
                    "method": "blacklist",
                    "engine_name": "K7GW",
                    "engine_version": "12.155.51808",
                    "engine_update": "20240425",
                    "category": "undetected",
                    "result": null
                },
                "K7AntiVirus": {
                    "method": "blacklist",
                    "engine_name": "K7AntiVirus",
                    "engine_version": "12.155.51809",
                    "engine_update": "20240425",
                    "category": "undetected",
                    "result": null
                },
                "Baidu": {
                    "method": "blacklist",
                    "engine_name": "Baidu",
                    "engine_version": "1.0.0.2",
                    "engine_update": "20190318",
                    "category": "undetected",
                    "result": null
                },
                "VirIT": {
                    "method": "blacklist",
                    "engine_name": "VirIT",
                    "engine_version": "9.5.690",
                    "engine_update": "20240424",
                    "category": "undetected",
                    "result": null
                },
                "Symantec": {
                    "method": "blacklist",
                    "engine_name": "Symantec",
                    "engine_version": "1.21.0.0",
                    "engine_update": "20240425",
                    "category": "undetected",
                    "result": null
                },
                "ESET-NOD32": {
                    "method": "blacklist",
                    "engine_name": "ESET-NOD32",
                    "engine_version": "29159",
                    "engine_update": "20240502",
                    "category": "undetected",
                    "result": null
                },
                "TrendMicro-HouseCall": {
                    "method": "blacklist",
                    "engine_name": "TrendMicro-HouseCall",
                    "engine_version": "10.0.0.1040",
                    "engine_update": "20240425",
                    "category": "undetected",
                    "result": null
                },
                "Cynet": {
                    "method": "blacklist",
                    "engine_name": "Cynet",
                    "engine_version": "4.0.1.1",
                    "engine_update": "20240425",
                    "category": "undetected",
                    "result": null
                },
                "Alibaba": {
                    "method": "blacklist",
                    "engine_name": "Alibaba",
                    "engine_version": "0.3.0.5",
                    "engine_update": "20190527",
                    "category": "undetected",
                    "result": null
                },
                "NANO-Antivirus": {
                    "method": "blacklist",
                    "engine_name": "NANO-Antivirus",
                    "engine_version": "1.0.146.25796",
                    "engine_update": "20240425",
                    "category": "undetected",
                    "result": null
                },
                "ViRobot": {
                    "method": "blacklist",
                    "engine_name": "ViRobot",
                    "engine_version": "2014.3.20.0",
                    "engine_update": "20240425",
                    "category": "undetected",
                    "result": null
                },
                "BitDefenderTheta": {
                    "method": "blacklist",
                    "engine_name": "BitDefenderTheta",
                    "engine_version": "7.2.37796.0",
                    "engine_update": "20240422",
                    "category": "undetected",
                    "result": null
                },
                "VIPRE": {
                    "method": "blacklist",
                    "engine_name": "VIPRE",
                    "engine_version": "6.0.0.35",
                    "engine_update": "20240425",
                    "category": "undetected",
                    "result": null
                },
                "TrendMicro": {
                    "method": "blacklist",
                    "engine_name": "TrendMicro",
                    "engine_version": "11.0.0.1006",
                    "engine_update": "20240425",
                    "category": "undetected",
                    "result": null
                },
                "Ikarus": {
                    "method": "blacklist",
                    "engine_name": "Ikarus",
                    "engine_version": "6.3.12.0",
                    "engine_update": "20240425",
                    "category": "undetected",
                    "result": null
                },
                "Avira": {
                    "method": "blacklist",
                    "engine_name": "Avira",
                    "engine_version": "8.3.3.18",
                    "engine_update": "20240425",
                    "category": "undetected",
                    "result": null
                },
                "MAX": {
                    "method": "blacklist",
                    "engine_name": "MAX",
                    "engine_version": "2023.1.4.1",
                    "engine_update": "20240502",
                    "category": "undetected",
                    "result": null
                },
                "Antiy-AVL": {
                    "method": "blacklist",
                    "engine_name": "Antiy-AVL",
                    "engine_version": "3.0",
                    "engine_update": "20240425",
                    "category": "undetected",
                    "result": null
                },
                "Kingsoft": {
                    "method": "blacklist",
                    "engine_name": "Kingsoft",
                    "engine_version": "None",
                    "engine_update": "20230906",
                    "category": "undetected",
                    "result": null
                },
                "Gridinsoft": {
                    "method": "blacklist",
                    "engine_name": "Gridinsoft",
                    "engine_version": "1.0.172.174",
                    "engine_update": "20240425",
                    "category": "undetected",
                    "result": null
                },
                "Arcabit": {
                    "method": "blacklist",
                    "engine_name": "Arcabit",
                    "engine_version": "2022.0.0.18",
                    "engine_update": "20240502",
                    "category": "undetected",
                    "result": null
                },
                "SUPERAntiSpyware": {
                    "method": "blacklist",
                    "engine_name": "SUPERAntiSpyware",
                    "engine_version": "5.6.0.1032",
                    "engine_update": "20240425",
                    "category": "undetected",
                    "result": null
                },
                "Avast-Mobile": {
                    "method": "blacklist",
                    "engine_name": "Avast-Mobile",
                    "engine_version": "240425-04",
                    "engine_update": "20240425",
                    "category": "undetected",
                    "result": null
                },
                "AhnLab-V3": {
                    "method": "blacklist",
                    "engine_name": "AhnLab-V3",
                    "engine_version": "3.25.1.10473",
                    "engine_update": "20240425",
                    "category": "undetected",
                    "result": null
                },
                "Acronis": {
                    "method": "blacklist",
                    "engine_name": "Acronis",
                    "engine_version": "1.2.0.121",
                    "engine_update": "20240328",
                    "category": "undetected",
                    "result": null
                },
                "VBA32": {
                    "method": "blacklist",
                    "engine_name": "VBA32",
                    "engine_version": "5.0.0",
                    "engine_update": "20240502",
                    "category": "undetected",
                    "result": null
                },
                "TACHYON": {
                    "method": "blacklist",
                    "engine_name": "TACHYON",
                    "engine_version": "2024-04-25.02",
                    "engine_update": "20240425",
                    "category": "undetected",
                    "result": null
                },
                "Zoner": {
                    "method": "blacklist",
                    "engine_name": "Zoner",
                    "engine_version": "2.2.2.0",
                    "engine_update": "20240425",
                    "category": "undetected",
                    "result": null
                },
                "Tencent": {
                    "method": "blacklist",
                    "engine_name": "Tencent",
                    "engine_version": "1.0.0.1",
                    "engine_update": "20240425",
                    "category": "undetected",
                    "result": null
                },
                "Yandex": {
                    "method": "blacklist",
                    "engine_name": "Yandex",
                    "engine_version": "5.5.2.24",
                    "engine_update": "20240502",
                    "category": "undetected",
                    "result": null
                },
                "SentinelOne": {
                    "method": "blacklist",
                    "engine_name": "SentinelOne",
                    "engine_version": "24.2.1.1",
                    "engine_update": "20240417",
                    "category": "undetected",
                    "result": null
                },
                "MaxSecure": {
                    "method": "blacklist",
                    "engine_name": "MaxSecure",
                    "engine_version": "1.0.0.1",
                    "engine_update": "20240425",
                    "category": "undetected",
                    "result": null
                },
                "Fortinet": {
                    "method": "blacklist",
                    "engine_name": "Fortinet",
                    "engine_version": "None",
                    "engine_update": "20240425",
                    "category": "undetected",
                    "result": null
                },
                "Panda": {
                    "method": "blacklist",
                    "engine_name": "Panda",
                    "engine_version": "4.6.4.2",
                    "engine_update": "20240502",
                    "category": "undetected",
                    "result": null
                },
                "CrowdStrike": {
                    "method": "blacklist",
                    "engine_name": "CrowdStrike",
                    "engine_version": "1.0",
                    "engine_update": "20231026",
                    "category": "undetected",
                    "result": null
                },
                "alibabacloud": {
                    "method": "blacklist",
                    "engine_name": "alibabacloud",
                    "engine_version": "2.0.3",
                    "engine_update": "20240418",
                    "category": "undetected",
                    "result": null
                },
                "ZoneAlarm": {
                    "method": "blacklist",
                    "engine_name": "ZoneAlarm",
                    "engine_version": "1.0",
                    "engine_update": "20240502",
                    "category": "confirmed-timeout",
                    "result": null
                },
                "DrWeb": {
                    "method": "blacklist",
                    "engine_name": "DrWeb",
                    "engine_version": "7.0.62.1180",
                    "engine_update": "20240502",
                    "category": "confirmed-timeout",
                    "result": null
                },
                "GData": {
                    "method": "blacklist",
                    "engine_name": "GData",
                    "engine_version": null,
                    "engine_update": "20240502",
                    "category": "confirmed-timeout",
                    "result": null
                },
                "Zillya": {
                    "method": "blacklist",
                    "engine_name": "Zillya",
                    "engine_version": "2.0.0.5103",
                    "engine_update": "20240502",
                    "category": "confirmed-timeout",
                    "result": null
                },
                "Sophos": {
                    "method": "blacklist",
                    "engine_name": "Sophos",
                    "engine_version": "2.4.3.0",
                    "engine_update": "20240502",
                    "category": "confirmed-timeout",
                    "result": null
                },
                "DeepInstinct": {
                    "method": "blacklist",
                    "engine_name": "DeepInstinct",
                    "engine_version": "5.0.0.8",
                    "engine_update": "20240502",
                    "category": "confirmed-timeout",
                    "result": null
                },
                "Emsisoft": {
                    "method": "blacklist",
                    "engine_name": "Emsisoft",
                    "engine_version": "2024.1.0.53752",
                    "engine_update": "20240502",
                    "category": "confirmed-timeout",
                    "result": null
                },
                "FireEye": {
                    "method": "blacklist",
                    "engine_name": "FireEye",
                    "engine_version": "35.47.0.0",
                    "engine_update": "20240502",
                    "category": "confirmed-timeout",
                    "result": null
                },
                "Kaspersky": {
                    "method": "blacklist",
                    "engine_name": "Kaspersky",
                    "engine_version": "22.0.1.28",
                    "engine_update": "20240502",
                    "category": "confirmed-timeout",
                    "result": null
                },
                "BitDefender": {
                    "method": "blacklist",
                    "engine_name": "BitDefender",
                    "engine_version": "7.2",
                    "engine_update": "20240502",
                    "category": "confirmed-timeout",
                    "result": null
                },
                "Skyhigh": {
                    "method": "blacklist",
                    "engine_name": "Skyhigh",
                    "engine_version": null,
                    "engine_update": "20240502",
                    "category": "confirmed-timeout",
                    "result": null
                },
                "McAfee": {
                    "method": "blacklist",
                    "engine_name": "McAfee",
                    "engine_version": "6.0.6.653",
                    "engine_update": "20240502",
                    "category": "confirmed-timeout",
                    "result": null
                },
                "Jiangmin": {
                    "method": "blacklist",
                    "engine_name": "Jiangmin",
                    "engine_version": null,
                    "engine_update": "20240502",
                    "category": "confirmed-timeout",
                    "result": null
                },
                "Varist": {
                    "method": "blacklist",
                    "engine_name": "Varist",
                    "engine_version": "6.5.1.2",
                    "engine_update": "20240502",
                    "category": "confirmed-timeout",
                    "result": null
                },
                "Rising": {
                    "method": "blacklist",
                    "engine_name": "Rising",
                    "engine_version": "25.0.0.27",
                    "engine_update": "20240502",
                    "category": "confirmed-timeout",
                    "result": null
                },
                "Avast": {
                    "method": "blacklist",
                    "engine_name": "Avast",
                    "engine_version": "23.9.8494.0",
                    "engine_update": "20240502",
                    "category": "confirmed-timeout",
                    "result": null
                },
                "AVG": {
                    "method": "blacklist",
                    "engine_name": "AVG",
                    "engine_version": "23.9.8494.0",
                    "engine_update": "20240502",
                    "category": "confirmed-timeout",
                    "result": null
                },
                "Xcitium": {
                    "method": "blacklist",
                    "engine_name": "Xcitium",
                    "engine_version": null,
                    "engine_update": "20240502",
                    "category": "confirmed-timeout",
                    "result": null
                },
                "Microsoft": {
                    "method": "blacklist",
                    "engine_name": "Microsoft",
                    "engine_version": "1.1.24030.4",
                    "engine_update": "20240502",
                    "category": "confirmed-timeout",
                    "result": null
                },
                "SymantecMobileInsight": {
                    "method": "blacklist",
                    "engine_name": "SymantecMobileInsight",
                    "engine_version": "2.0",
                    "engine_update": "20240103",
                    "category": "type-unsupported",
                    "result": null
                },
                "BitDefenderFalx": {
                    "method": "blacklist",
                    "engine_name": "BitDefenderFalx",
                    "engine_version": "2.0.936",
                    "engine_update": "20240128",
                    "category": "type-unsupported",
                    "result": null
                },
                "Elastic": {
                    "method": "blacklist",
                    "engine_name": "Elastic",
                    "engine_version": "4.0.142",
                    "engine_update": "20240425",
                    "category": "type-unsupported",
                    "result": null
                },
                "Webroot": {
                    "method": "blacklist",
                    "engine_name": "Webroot",
                    "engine_version": "1.0.0.403",
                    "engine_update": "20240425",
                    "category": "type-unsupported",
                    "result": null
                },
                "APEX": {
                    "method": "blacklist",
                    "engine_name": "APEX",
                    "engine_version": "6.525",
                    "engine_update": "20240425",
                    "category": "type-unsupported",
                    "result": null
                },
                "Paloalto": {
                    "method": "blacklist",
                    "engine_name": "Paloalto",
                    "engine_version": "0.9.0.1003",
                    "engine_update": "20240425",
                    "category": "type-unsupported",
                    "result": null
                },
                "Trapmine": {
                    "method": "blacklist",
                    "engine_name": "Trapmine",
                    "engine_version": "4.0.16.96",
                    "engine_update": "20240223",
                    "category": "type-unsupported",
                    "result": null
                },
                "Cylance": {
                    "method": "blacklist",
                    "engine_name": "Cylance",
                    "engine_version": "2.0.0.0",
                    "engine_update": "20240425",
                    "category": "type-unsupported",
                    "result": null
                }
            },
            "trid": [
                {
                    "file_type": "Java Archive",
                    "probability": 72.9
                },
                {
                    "file_type": "ZIP compressed archive",
                    "probability": 21.6
                },
                {
                    "file_type": "PrintFox/Pagefox bitmap (640x800)",
                    "probability": 5.4
                }
            ],
            "ssdeep": "3145728:Z0iuEWfFjoDh684Iy+LxLU5OT2i41/+0c3j+orJZe:zuEWfZoD++LhUQC3w0SBJZe",
            "times_submitted": 1,
            "unique_sources": 1,
            "last_analysis_date": 1714057823,
            "sandbox_verdicts": {
                "Zenbox Linux": {
                    "category": "harmless",
                    "malware_classification": [
                        "CLEAN"
                    ],
                    "sandbox_name": "Zenbox Linux",
                    "confidence": 100
                },
                "C2AE": {
                    "category": "undetected",
                    "malware_classification": [
                        "UNKNOWN_VERDICT"
                    ],
                    "sandbox_name": "C2AE"
                }
            },
            "md5": "a9d4bbb94de940dbe6245d6998055ad1",
            "tags": [
                "jar",
                "contains-macho",
                "mac-app",
                "signed"
            ],
            "last_analysis_stats": {
                "malicious": 0,
                "suspicious": 0,
                "undetected": 45,
                "harmless": 0,
                "timeout": 0,
                "confirmed-timeout": 19,
                "failure": 0,
                "type-unsupported": 8
            },
            "meaningful_name": "com.wireframesketcher.studio",
            "bundle_info": {
                "highest_datetime": "2024-04-25 16:03:16",
                "lowest_datetime": "2018-03-15 09:46:16",
                "num_children": 714,
                "extensions": {
                    "cfg": 1,
                    "gz": 4,
                    "ini": 2,
                    "inf": 2,
                    "txt": 4,
                    "bfc": 1,
                    "jar": 223,
                    "1": 1,
                    "0": 1,
                    "0/": 2,
                    "css": 22,
                    "xml": 22,
                    "dat": 2,
                    "ja": 1,
                    "png": 4,
                    "src": 1,
                    "MF": 24,
                    "RSA": 23,
                    "so": 2,
                    "asc": 3,
                    "SF": 23,
                    "1/": 1
                },
                "file_types": {
                    "XML": 40,
                    "ZIP": 224,
                    "unknown": 164,
                    "Java Bytecode": 125,
                    "directory": 91,
                    "HTML": 29,
                    "Mac OS X Executable": 37,
                    "PNG": 4
                },
                "type": "JAR",
                "uncompressed_size": 157337288
            },
            "signature_info": {
                "verified": "Valid",
                "signers": "Petru Severin; Apple Inc.; Apple Inc.",
                "signers details": [
                    {
                        "name": "Petru Severin",
                        "algorithm": "sha256WithRSAEncryption",
                        "status": "Valid",
                        "valid from": "09:31 AM 09/21/2023",
                        "valid to": "09:31 AM 09/21/2028",
                        "serial number": "1B E3 0D 34 52 7D FB 26 2E A8 92 D5 F4 60 5A 97",
                        "cert issuer": "Apple Inc.",
                        "thumbprint": "B6DAB41FC103A3FA8F394C045E03C1C9C9D29639"
                    },
                    {
                        "name": "Apple Inc.",
                        "algorithm": "sha256WithRSAEncryption",
                        "status": "Valid",
                        "valid from": "06:55 PM 09/22/2021",
                        "valid to": "12:00 AM 09/17/2031",
                        "serial number": "7F B4 00 3F CD 97 49 7A CB 83 4D 92 A4 8A 78 73 C2 84 5D 43",
                        "cert issuer": "Apple Inc.",
                        "thumbprint": "5B45F61068B29FCC8FFFF1A7E99B78DA9E9C4635"
                    },
                    {
                        "name": "Apple Inc.",
                        "algorithm": "sha1WithRSAEncryption",
                        "status": "Valid",
                        "valid from": "09:40 PM 04/25/2006",
                        "valid to": "09:40 PM 02/09/2035",
                        "serial number": "2",
                        "cert issuer": "Apple Inc.",
                        "thumbprint": "611E5B662C593A08FF58D14AE22452D198DF6C60"
                    }
                ],
                "Identifier": "com.wireframesketcher.studio",
                "Authority": "Apple Root CA",
                "TeamIdentifier": "RK7JEGR935",
                "Format": "app bundle with Mach-O thin (arm64)",
                "CDHash": "43c7bc00769d7365fc76fa5be654ac12fded5b09",
                "Hash choices": "sha1,sha256",
                "CandidateCDHash sha256": "43c7bc00769d7365fc76fa5be654ac12fded5b09",
                "CandidateCDHashFull sha256": "43c7bc00769d7365fc76fa5be654ac12fded5b09ab6b7f4df36e82f09a8fb9fe",
                "CandidateCDHash sha1": "f97a03b5cef04e29e37dad575018411adc08b00d",
                "CandidateCDHashFull sha1": "f97a03b5cef04e29e37dad575018411adc08b00d",
                "Info.plist entries": "16",
                "CMSDigest": "e9f21931f7cf307cb3fc04979e33677e787adfe2adce2c4fbc2197eb766b2ef1",
                "CMSDigestType": "2"
            },
            "last_modification_date": 1714662871,
            "type_extension": "jar"
        }
    }
}