{
    "data": {
        "attributes": {
            "type_description": "Macintosh Disk Image",
            "tlsh": "T194563376A3DC6C01F515017106BF5B1ADD3DEC67F8ABD25A42145A8E38BB788BE0EC81",
            "vhash": "edf66af6c50e09f8b1a31144c57943be",
            "trid": [
                {
                    "file_type": "ZLIB compressed data (var. 4)",
                    "probability": 100.0
                }
            ],
            "names": [
                "69c0287f-cb32-4fef-a90e-af8c650f3838",
                "OnlySwitch.dmg"
            ],
            "signature_info": {
                "VersionMin": "786432",
                "CDHash": "d88bf5100e297440f7c9c84a736faac96aa0f591",
                "signers": "Bo Liu; Apple Inc.; Apple Inc.",
                "Runtime Version": "12.3.0",
                "TeamIdentifier": "B22726TNGH",
                "CandidateCDHash sha256": "d88bf5100e297440f7c9c84a736faac96aa0f591",
                "Hash choices": "sha256",
                "Format": "app bundle with Mach-O universal (x86_64 arm64)",
                "Timestamp": "Jun 18, 2022 at 6:02:54 AM",
                "Signature size": "8962",
                "Executable Segment base": "0",
                "Page size": "4096",
                "VersionPlatform": "1",
                "CMSDigest": "d88bf5100e297440f7c9c84a736faac96aa0f591911929d7450e375598f47cc9",
                "CMSDigestType": "2",
                "Executable Segment flags": "0x1",
                "CandidateCDHashFull sha256": "d88bf5100e297440f7c9c84a736faac96aa0f591911929d7450e375598f47cc9",
                "verified": "Valid",
                "VersionSDK": "787200",
                "Identifier": "jacklandrin.OnlySwitch",
                "signers details": [
                    {
                        "valid usage": "",
                        "status": "Valid",
                        "name": "Bo Liu",
                        "algorithm": "sha256WithRSAEncryption",
                        "valid from": "06:25 PM 01/18/2022",
                        "valid to": "06:25 PM 01/19/2027",
                        "serial number": "52 4D E2 DD 98 58 9F DB",
                        "cert issuer": "Apple Inc.",
                        "thumbprint": "0511D76A816CEA9DF2A66FF68E0BFC066FA5DC7F"
                    },
                    {
                        "valid usage": "",
                        "status": "Valid",
                        "name": "Apple Inc.",
                        "algorithm": "sha256WithRSAEncryption",
                        "valid from": "10:12 PM 02/01/2012",
                        "valid to": "10:12 PM 02/01/2027",
                        "serial number": "18 7A A9 A8 C2 96 21 0C",
                        "cert issuer": "Apple Inc.",
                        "thumbprint": "3B166C3B7DC4B751C9FE2AFAB9135641E388E186"
                    },
                    {
                        "valid usage": "",
                        "status": "Valid",
                        "name": "Apple Inc.",
                        "algorithm": "sha1WithRSAEncryption",
                        "valid from": "09:40 PM 04/25/2006",
                        "valid to": "09:40 PM 02/09/2035",
                        "serial number": "2",
                        "cert issuer": "Apple Inc.",
                        "thumbprint": "611E5B662C593A08FF58D14AE22452D198DF6C60"
                    }
                ],
                "Info.plist entries": "31",
                "Authority": "Apple Root CA",
                "Executable Segment limit": "2260992"
            },
            "last_modification_date": 1655728424,
            "type_tag": "dmg",
            "times_submitted": 1,
            "total_votes": {
                "harmless": 0,
                "malicious": 0
            },
            "size": 6153334,
            "type_extension": "dmg",
            "dmg_info": {
                "blkx": [
                    {
                        "attributes": "0x0050",
                        "name": "Driver Descriptor Map (DDM : 0)"
                    },
                    {
                        "attributes": "0x0050",
                        "name": "Apple (Apple_partition_map : 1)"
                    },
                    {
                        "attributes": "0x0050",
                        "name": "disk image (Apple_HFS : 2)"
                    }
                ],
                "plst": [
                    {
                        "attributes": "0x0050",
                        "name": "ID:0"
                    }
                ],
                "running_data_fork_offset": 0,
                "plst_keys": [
                    "resource-fork"
                ],
                "dmg_version": 4,
                "xml_offset": 6136283,
                "data_fork_offset": 0,
                "rsrc_fork_offset": 0,
                "resourcefork_keys": [
                    "blkx",
                    "plst"
                ],
                "xml_length": 5246,
                "data_fork_length": 6136283,
                "hfs": {
                    "unreadable_files": 0,
                    "info_plist": {
                        "CFBundleInfoDictionaryVersion": "6.0",
                        "NSHumanReadableCopyright": "Copyright \u00a9 2021-2022 Jacklandrin",
                        "DTXcodeBuild": "13F100",
                        "CFBundleSupportedPlatforms": "['MacOSX']",
                        "CFBundleIdentifier": "jacklandrin.OnlySwitch",
                        "DTSDKName": "macosx12.3",
                        "DTPlatformVersion": "12.3",
                        "CFBundleShortVersionString": "2.3.2",
                        "CFBundleDisplayName": "Only Switch",
                        "BuildMachineOSBuild": "21F79",
                        "LSUIElement": "True",
                        "CFBundleExecutable": "OnlySwitch",
                        "LSMinimumSystemVersion": "12.0",
                        "NSAppTransportSecurity": "{'NSAllowsArbitraryLoads': True}",
                        "CFBundleVersion": "59",
                        "NSAppleEventsUsageDescription": "Only Switch requests Apple Event usage to switch dark mode",
                        "CFBundleIconFile": "AppIcon",
                        "DTPlatformBuild": "13F100",
                        "DTXcode": "1341",
                        "CFBundleDevelopmentRegion": "en",
                        "CFBundleURLTypes": "[{'CFBundleURLSchemes': ['onlyswitch']}]",
                        "DTPlatformName": "macosx",
                        "CFBundleIconName": "AppIcon",
                        "LSApplicationCategoryType": "public.app-category.utilities",
                        "DTCompiler": "com.apple.compilers.llvm.clang.1_0",
                        "NSUserActivityTypes": "['GetWallpaperImageIntent', 'GetWallpaperUrlIntent', 'IsDarkModeIntent', 'SetDarkModeIntent']",
                        "DTSDKBuild": "21E226",
                        "NSBluetoothAlwaysUsageDescription": "Only Switch requests Bluetooth usage to switch Airpods connection",
                        "CFBundleName": "OnlySwitch",
                        "CFBundlePackageType": "APPL",
                        "NSPrincipalClass": "NSApplication"
                    },
                    "main_executable": {
                        "path": "/Only Switch.app/Contents/MacOS/OnlySwitch",
                        "sha256": "2f233f326298195ec4f3a642bfa0acc0b4ef6784d1cb02f331d875dc058e37c7",
                        "size": 5706064
                    },
                    "num_files": 48
                },
                "rsrc_fork_length": 0
            },
            "last_submission_date": 1655643323,
            "last_analysis_results": {
                "Bkav": {
                    "category": "undetected",
                    "engine_name": "Bkav",
                    "engine_version": "1.3.0.9899",
                    "result": null,
                    "method": "blacklist",
                    "engine_update": "20220618"
                },
                "Lionic": {
                    "category": "undetected",
                    "engine_name": "Lionic",
                    "engine_version": "7.5",
                    "result": null,
                    "method": "blacklist",
                    "engine_update": "20220617"
                },
                "tehtris": {
                    "category": "type-unsupported",
                    "engine_name": "tehtris",
                    "engine_version": null,
                    "result": null,
                    "method": "blacklist",
                    "engine_update": "20220619"
                },
                "MicroWorld-eScan": {
                    "category": "undetected",
                    "engine_name": "MicroWorld-eScan",
                    "engine_version": "14.0.409.0",
                    "result": null,
                    "method": "blacklist",
                    "engine_update": "20220619"
                },
                "ClamAV": {
                    "category": "failure",
                    "engine_name": "ClamAV",
                    "engine_version": "0.105.0.0",
                    "result": null,
                    "method": "blacklist",
                    "engine_update": "20220619"
                },
                "CMC": {
                    "category": "undetected",
                    "engine_name": "CMC",
                    "engine_version": "2.10.2019.1",
                    "result": null,
                    "method": "blacklist",
                    "engine_update": "20211026"
                },
                "CAT-QuickHeal": {
                    "category": "undetected",
                    "engine_name": "CAT-QuickHeal",
                    "engine_version": "14.00",
                    "result": null,
                    "method": "blacklist",
                    "engine_update": "20220619"
                },
                "McAfee": {
                    "category": "undetected",
                    "engine_name": "McAfee",
                    "engine_version": "6.0.6.653",
                    "result": null,
                    "method": "blacklist",
                    "engine_update": "20220619"
                },
                "Malwarebytes": {
                    "category": "undetected",
                    "engine_name": "Malwarebytes",
                    "engine_version": "4.3.3.37",
                    "result": null,
                    "method": "blacklist",
                    "engine_update": "20220619"
                },
                "Zillya": {
                    "category": "failure",
                    "engine_name": "Zillya",
                    "engine_version": "2.0.0.4653",
                    "result": null,
                    "method": "blacklist",
                    "engine_update": "20220617"
                },
                "Sangfor": {
                    "category": "undetected",
                    "engine_name": "Sangfor",
                    "engine_version": "2.14.0.0",
                    "result": null,
                    "method": "blacklist",
                    "engine_update": "20220602"
                },
                "K7AntiVirus": {
                    "category": "undetected",
                    "engine_name": "K7AntiVirus",
                    "engine_version": "12.19.42911",
                    "result": null,
                    "method": "blacklist",
                    "engine_update": "20220619"
                },
                "Alibaba": {
                    "category": "type-unsupported",
                    "engine_name": "Alibaba",
                    "engine_version": "0.3.0.5",
                    "result": null,
                    "method": "blacklist",
                    "engine_update": "20190527"
                },
                "K7GW": {
                    "category": "undetected",
                    "engine_name": "K7GW",
                    "engine_version": "12.19.42912",
                    "result": null,
                    "method": "blacklist",
                    "engine_update": "20220619"
                },
                "Trustlook": {
                    "category": "type-unsupported",
                    "engine_name": "Trustlook",
                    "engine_version": "1.0",
                    "result": null,
                    "method": "blacklist",
                    "engine_update": "20220619"
                },
                "Baidu": {
                    "category": "undetected",
                    "engine_name": "Baidu",
                    "engine_version": "1.0.0.2",
                    "result": null,
                    "method": "blacklist",
                    "engine_update": "20190318"
                },
                "VirIT": {
                    "category": "undetected",
                    "engine_name": "VirIT",
                    "engine_version": "9.5.219",
                    "result": null,
                    "method": "blacklist",
                    "engine_update": "20220617"
                },
                "Cyren": {
                    "category": "undetected",
                    "engine_name": "Cyren",
                    "engine_version": "6.5.1.2",
                    "result": null,
                    "method": "blacklist",
                    "engine_update": "20220619"
                },
                "SymantecMobileInsight": {
                    "category": "type-unsupported",
                    "engine_name": "SymantecMobileInsight",
                    "engine_version": "2.0",
                    "result": null,
                    "method": "blacklist",
                    "engine_update": "20220208"
                },
                "Elastic": {
                    "category": "type-unsupported",
                    "engine_name": "Elastic",
                    "engine_version": "4.0.39",
                    "result": null,
                    "method": "blacklist",
                    "engine_update": "20220614"
                },
                "ESET-NOD32": {
                    "category": "undetected",
                    "engine_name": "ESET-NOD32",
                    "engine_version": "25460",
                    "result": null,
                    "method": "blacklist",
                    "engine_update": "20220619"
                },
                "APEX": {
                    "category": "type-unsupported",
                    "engine_name": "APEX",
                    "engine_version": "6.304",
                    "result": null,
                    "method": "blacklist",
                    "engine_update": "20220619"
                },
                "TrendMicro-HouseCall": {
                    "category": "undetected",
                    "engine_name": "TrendMicro-HouseCall",
                    "engine_version": "10.0.0.1040",
                    "result": null,
                    "method": "blacklist",
                    "engine_update": "20220619"
                },
                "Avast": {
                    "category": "undetected",
                    "engine_name": "Avast",
                    "engine_version": "21.1.5827.0",
                    "result": null,
                    "method": "blacklist",
                    "engine_update": "20220619"
                },
                "Cynet": {
                    "category": "undetected",
                    "engine_name": "Cynet",
                    "engine_version": "4.0.0.27",
                    "result": null,
                    "method": "blacklist",
                    "engine_update": "20220619"
                },
                "Kaspersky": {
                    "category": "undetected",
                    "engine_name": "Kaspersky",
                    "engine_version": "21.0.1.45",
                    "result": null,
                    "method": "blacklist",
                    "engine_update": "20220619"
                },
                "BitDefender": {
                    "category": "undetected",
                    "engine_name": "BitDefender",
                    "engine_version": "7.2",
                    "result": null,
                    "method": "blacklist",
                    "engine_update": "20220619"
                },
                "NANO-Antivirus": {
                    "category": "undetected",
                    "engine_name": "NANO-Antivirus",
                    "engine_version": "1.0.146.25588",
                    "result": null,
                    "method": "blacklist",
                    "engine_update": "20220619"
                },
                "ViRobot": {
                    "category": "undetected",
                    "engine_name": "ViRobot",
                    "engine_version": "2014.3.20.0",
                    "result": null,
                    "method": "blacklist",
                    "engine_update": "20220619"
                },
                "Tencent": {
                    "category": "undetected",
                    "engine_name": "Tencent",
                    "engine_version": "1.0.0.1",
                    "result": null,
                    "method": "blacklist",
                    "engine_update": "20220619"
                },
                "Ad-Aware": {
                    "category": "undetected",
                    "engine_name": "Ad-Aware",
                    "engine_version": "3.0.21.193",
                    "result": null,
                    "method": "blacklist",
                    "engine_update": "20220619"
                },
                "Emsisoft": {
                    "category": "undetected",
                    "engine_name": "Emsisoft",
                    "engine_version": "2021.5.0.7597",
                    "result": null,
                    "method": "blacklist",
                    "engine_update": "20220619"
                },
                "Comodo": {
                    "category": "undetected",
                    "engine_name": "Comodo",
                    "engine_version": "34728",
                    "result": null,
                    "method": "blacklist",
                    "engine_update": "20220619"
                },
                "F-Secure": {
                    "category": "undetected",
                    "engine_name": "F-Secure",
                    "engine_version": "18.10.978.51",
                    "result": null,
                    "method": "blacklist",
                    "engine_update": "20220619"
                },
                "DrWeb": {
                    "category": "undetected",
                    "engine_name": "DrWeb",
                    "engine_version": "7.0.56.4040",
                    "result": null,
                    "method": "blacklist",
                    "engine_update": "20220619"
                },
                "BitDefenderTheta": {
                    "category": "undetected",
                    "engine_name": "BitDefenderTheta",
                    "engine_version": "7.2.37796.0",
                    "result": null,
                    "method": "blacklist",
                    "engine_update": "20220614"
                },
                "TrendMicro": {
                    "category": "undetected",
                    "engine_name": "TrendMicro",
                    "engine_version": "11.0.0.1006",
                    "result": null,
                    "method": "blacklist",
                    "engine_update": "20220619"
                },
                "McAfee-GW-Edition": {
                    "category": "undetected",
                    "engine_name": "McAfee-GW-Edition",
                    "engine_version": "v2019.1.2+3728",
                    "result": null,
                    "method": "blacklist",
                    "engine_update": "20220618"
                },
                "SentinelOne": {
                    "category": "type-unsupported",
                    "engine_name": "SentinelOne",
                    "engine_version": "22.2.1.2",
                    "result": null,
                    "method": "blacklist",
                    "engine_update": "20220330"
                },
                "Trapmine": {
                    "category": "type-unsupported",
                    "engine_name": "Trapmine",
                    "engine_version": "3.5.50.94",
                    "result": null,
                    "method": "blacklist",
                    "engine_update": "20220526"
                },
                "FireEye": {
                    "category": "undetected",
                    "engine_name": "FireEye",
                    "engine_version": "35.24.1.0",
                    "result": null,
                    "method": "blacklist",
                    "engine_update": "20220619"
                },
                "Sophos": {
                    "category": "undetected",
                    "engine_name": "Sophos",
                    "engine_version": "1.4.1.0",
                    "result": null,
                    "method": "blacklist",
                    "engine_update": "20220619"
                },
                "Paloalto": {
                    "category": "type-unsupported",
                    "engine_name": "Paloalto",
                    "engine_version": "0.9.0.1003",
                    "result": null,
                    "method": "blacklist",
                    "engine_update": "20220619"
                },
                "Avast-Mobile": {
                    "category": "type-unsupported",
                    "engine_name": "Avast-Mobile",
                    "engine_version": "220619-02",
                    "result": null,
                    "method": "blacklist",
                    "engine_update": "20220619"
                },
                "Jiangmin": {
                    "category": "undetected",
                    "engine_name": "Jiangmin",
                    "engine_version": "16.0.100",
                    "result": null,
                    "method": "blacklist",
                    "engine_update": "20220618"
                },
                "Webroot": {
                    "category": "type-unsupported",
                    "engine_name": "Webroot",
                    "engine_version": "1.0.0.403",
                    "result": null,
                    "method": "blacklist",
                    "engine_update": "20220619"
                },
                "Avira": {
                    "category": "undetected",
                    "engine_name": "Avira",
                    "engine_version": "8.3.3.14",
                    "result": null,
                    "method": "blacklist",
                    "engine_update": "20220619"
                },
                "Kingsoft": {
                    "category": "undetected",
                    "engine_name": "Kingsoft",
                    "engine_version": "2017.9.26.565",
                    "result": null,
                    "method": "blacklist",
                    "engine_update": "20220619"
                },
                "Microsoft": {
                    "category": "undetected",
                    "engine_name": "Microsoft",
                    "engine_version": "1.1.19200.6",
                    "result": null,
                    "method": "blacklist",
                    "engine_update": "20220619"
                },
                "Gridinsoft": {
                    "category": "undetected",
                    "engine_name": "Gridinsoft",
                    "engine_version": "1.0.81.174",
                    "result": null,
                    "method": "blacklist",
                    "engine_update": "20220619"
                },
                "Arcabit": {
                    "category": "undetected",
                    "engine_name": "Arcabit",
                    "engine_version": "1.0.0.889",
                    "result": null,
                    "method": "blacklist",
                    "engine_update": "20220619"
                },
                "SUPERAntiSpyware": {
                    "category": "undetected",
                    "engine_name": "SUPERAntiSpyware",
                    "engine_version": "5.6.0.1032",
                    "result": null,
                    "method": "blacklist",
                    "engine_update": "20220618"
                },
                "ZoneAlarm": {
                    "category": "undetected",
                    "engine_name": "ZoneAlarm",
                    "engine_version": "1.0",
                    "result": null,
                    "method": "blacklist",
                    "engine_update": "20220619"
                },
                "GData": {
                    "category": "undetected",
                    "engine_name": "GData",
                    "engine_version": "A:25.33311B:27.27772",
                    "result": null,
                    "method": "blacklist",
                    "engine_update": "20220619"
                },
                "TACHYON": {
                    "category": "undetected",
                    "engine_name": "TACHYON",
                    "engine_version": "2022-06-19.02",
                    "result": null,
                    "method": "blacklist",
                    "engine_update": "20220619"
                },
                "BitDefenderFalx": {
                    "category": "type-unsupported",
                    "engine_name": "BitDefenderFalx",
                    "engine_version": "2.0.936",
                    "result": null,
                    "method": "blacklist",
                    "engine_update": "20220103"
                },
                "AhnLab-V3": {
                    "category": "undetected",
                    "engine_name": "AhnLab-V3",
                    "engine_version": "3.22.0.10282",
                    "result": null,
                    "method": "blacklist",
                    "engine_update": "20220619"
                },
                "Acronis": {
                    "category": "undetected",
                    "engine_name": "Acronis",
                    "engine_version": "1.2.0.108",
                    "result": null,
                    "method": "blacklist",
                    "engine_update": "20220426"
                },
                "VBA32": {
                    "category": "undetected",
                    "engine_name": "VBA32",
                    "engine_version": "5.0.0",
                    "result": null,
                    "method": "blacklist",
                    "engine_update": "20220617"
                },
                "ALYac": {
                    "category": "undetected",
                    "engine_name": "ALYac",
                    "engine_version": "1.1.3.1",
                    "result": null,
                    "method": "blacklist",
                    "engine_update": "20220619"
                },
                "MAX": {
                    "category": "undetected",
                    "engine_name": "MAX",
                    "engine_version": "2019.9.16.1",
                    "result": null,
                    "method": "blacklist",
                    "engine_update": "20220619"
                },
                "Cylance": {
                    "category": "type-unsupported",
                    "engine_name": "Cylance",
                    "engine_version": "2.3.1.101",
                    "result": null,
                    "method": "blacklist",
                    "engine_update": "20220619"
                },
                "Zoner": {
                    "category": "undetected",
                    "engine_name": "Zoner",
                    "engine_version": "2.2.2.0",
                    "result": null,
                    "method": "blacklist",
                    "engine_update": "20220618"
                },
                "Rising": {
                    "category": "undetected",
                    "engine_name": "Rising",
                    "engine_version": "25.0.0.27",
                    "result": null,
                    "method": "blacklist",
                    "engine_update": "20220619"
                },
                "Yandex": {
                    "category": "undetected",
                    "engine_name": "Yandex",
                    "engine_version": "5.5.2.24",
                    "result": null,
                    "method": "blacklist",
                    "engine_update": "20220619"
                },
                "Ikarus": {
                    "category": "undetected",
                    "engine_name": "Ikarus",
                    "engine_version": "6.0.24.0",
                    "result": null,
                    "method": "blacklist",
                    "engine_update": "20220619"
                },
                "MaxSecure": {
                    "category": "undetected",
                    "engine_name": "MaxSecure",
                    "engine_version": "1.0.0.1",
                    "result": null,
                    "method": "blacklist",
                    "engine_update": "20220618"
                },
                "Fortinet": {
                    "category": "undetected",
                    "engine_name": "Fortinet",
                    "engine_version": "6.2.142.0",
                    "result": null,
                    "method": "blacklist",
                    "engine_update": "20220619"
                },
                "Cybereason": {
                    "category": "type-unsupported",
                    "engine_name": "Cybereason",
                    "engine_version": "1.2.449",
                    "result": null,
                    "method": "blacklist",
                    "engine_update": "20210330"
                },
                "Panda": {
                    "category": "undetected",
                    "engine_name": "Panda",
                    "engine_version": "4.6.4.2",
                    "result": null,
                    "method": "blacklist",
                    "engine_update": "20220619"
                },
                "CrowdStrike": {
                    "category": "type-unsupported",
                    "engine_name": "CrowdStrike",
                    "engine_version": "1.0",
                    "result": null,
                    "method": "blacklist",
                    "engine_update": null
                }
            },
            "sandbox_verdicts": {
                "OS X Sandbox": {
                    "category": "harmless",
                    "sandbox_name": "OS X Sandbox",
                    "malware_classification": [
                        "CLEAN"
                    ]
                }
            },
            "sha256": "ab9fb8e3146ef6715bbb22292e3b7599270cc34f31aa02bb378f683577407f0a",
            "tags": [
                "contains-macho",
                "dmg",
                "signed"
            ],
            "last_analysis_date": 1655643323,
            "unique_sources": 1,
            "first_submission_date": 1655643323,
            "ssdeep": "98304:8BY+xcxLStdDOJ8cPwyMqL4uzsx9cwGoPd4sc+OujaV+r+6PaYzE2hTI0g:8+scRgm84ZMMFSynodxdaXsE6TIh",
            "md5": "3b7aa5b72e8d2523ef475774c03ec35e",
            "sha1": "29265b34225143c8e500027dd3e73d43890b5b02",
            "magic": "data",
            "last_analysis_stats": {
                "harmless": 0,
                "type-unsupported": 15,
                "suspicious": 0,
                "confirmed-timeout": 0,
                "timeout": 0,
                "failure": 2,
                "malicious": 0,
                "undetected": 54
            },
            "meaningful_name": "jacklandrin.OnlySwitch",
            "reputation": 0
        },
        "type": "file",
        "id": "ab9fb8e3146ef6715bbb22292e3b7599270cc34f31aa02bb378f683577407f0a",
        "links": {
            "self": "https://www.virustotal.com/api/v3/files/ab9fb8e3146ef6715bbb22292e3b7599270cc34f31aa02bb378f683577407f0a"
        }
    }
}